bruty/__init__.py
bruty/py.typed
bruty/services.py
bruty/version.py
bruty/entrypoints/__init__.py
bruty/entrypoints/cli.py
bruty/model/__init__.py
bruty-0.2.0.dist-info/LICENSE
bruty-0.2.0.dist-info/METADATA
bruty-0.2.0.dist-info/WHEEL
bruty-0.2.0.dist-info/entry_points.txt
bruty-0.2.0.dist-info/top_level.txt
bruty-0.2.0.dist-info/RECORD
