Metadata-Version: 2.1
Name: bruty
Version: 0.2.0
Summary: Bruteforce dynamic web applications with Selenium
Home-page: https://github.com/lyz-code/bruty
Author: Lyz
Author-email: lyz-code-security-advisories@riseup.net
License: GNU General Public License v3
Platform: UNKNOWN
Classifier: Development Status :: 2 - Pre-Alpha
Classifier: Intended Audience :: Developers
Classifier: License :: OSI Approved :: GNU General Public License v3 or later (GPLv3+)
Classifier: Operating System :: Unix
Classifier: Operating System :: POSIX
Classifier: Programming Language :: Python
Classifier: Programming Language :: Python :: 3
Classifier: Programming Language :: Python :: 3.6
Classifier: Programming Language :: Python :: 3.7
Classifier: Programming Language :: Python :: 3.8
Classifier: Topic :: Utilities
Classifier: Natural Language :: English
Requires-Python: >=3.6
License-File: LICENSE
Requires-Dist: selenium
Requires-Dist: Click
Requires-Dist: rich
